BenbanfaXuePythonXu/README.md
BenbanfaXuePythonXu/__init__.py
BenbanfaXuePythonXu/__main__.py
BenbanfaXuePythonXu/file.epub
BenbanfaXuePythonXu/index.html
BenbanfaXuePythonXu/css/__init__.py
BenbanfaXuePythonXu/css/annotations.css
BenbanfaXuePythonXu/css/main.css
BenbanfaXuePythonXu/css/normalize.css
BenbanfaXuePythonXu/css/popup.css
BenbanfaXuePythonXu/font/__init__.py
BenbanfaXuePythonXu/font/fontello.eot
BenbanfaXuePythonXu/font/fontello.svg
BenbanfaXuePythonXu/font/fontello.ttf
BenbanfaXuePythonXu/font/fontello.woff
BenbanfaXuePythonXu/img/__init__.py
BenbanfaXuePythonXu/img/annotator-glyph-sprite.png
BenbanfaXuePythonXu/img/annotator-icon-sprite.png
BenbanfaXuePythonXu/img/apple-touch-icon.png
BenbanfaXuePythonXu/img/cancelfullscreen.png
BenbanfaXuePythonXu/img/close.png
BenbanfaXuePythonXu/img/fullscreen.png
BenbanfaXuePythonXu/img/loader.gif
BenbanfaXuePythonXu/img/menu-icon.png
BenbanfaXuePythonXu/img/save.png
BenbanfaXuePythonXu/img/saved.png
BenbanfaXuePythonXu/img/settings-s.png
BenbanfaXuePythonXu/img/settings.png
BenbanfaXuePythonXu/img/star.png
BenbanfaXuePythonXu/js/__init__.py
BenbanfaXuePythonXu/js/epub.js
BenbanfaXuePythonXu/js/epub.min.js
BenbanfaXuePythonXu/js/epub.min.map
BenbanfaXuePythonXu/js/hooks.min.js
BenbanfaXuePythonXu/js/hooks.min.map
BenbanfaXuePythonXu/js/reader.js
BenbanfaXuePythonXu/js/reader.js.map
BenbanfaXuePythonXu/js/reader.min.js
BenbanfaXuePythonXu/js/reader.min.map
BenbanfaXuePythonXu/js/hooks/__init__.py
BenbanfaXuePythonXu/js/hooks/extensions/__init__.py
BenbanfaXuePythonXu/js/hooks/extensions/highlight.js
BenbanfaXuePythonXu/js/libs/__init__.py
BenbanfaXuePythonXu/js/libs/jquery.min.js
BenbanfaXuePythonXu/js/libs/localforage.min.js
BenbanfaXuePythonXu/js/libs/screenfull.js
BenbanfaXuePythonXu/js/libs/screenfull.min.js
BenbanfaXuePythonXu/js/libs/zip.min.js
BenbanfaXuePythonXu/js/plugins/__init__.py
BenbanfaXuePythonXu/js/plugins/hypothesis.js
BenbanfaXuePythonXu/js/plugins/search.js
benbanfa_xue_python_xu-2024.3.2.0.dist-info/METADATA
benbanfa_xue_python_xu-2024.3.2.0.dist-info/WHEEL
benbanfa_xue_python_xu-2024.3.2.0.dist-info/entry_points.txt
benbanfa_xue_python_xu-2024.3.2.0.dist-info/top_level.txt
benbanfa_xue_python_xu-2024.3.2.0.dist-info/RECORD
